fxtrade/__init__.py
fxtrade/interface/__init__.py
fxtrade/interface/bitflyer.py
fxtrade/interface/bitflyer_utils.py
fxtrade/math.py
fxtrade/utils.py
fxtrade-0.1.7.dist-info/LICENSE
fxtrade-0.1.7.dist-info/METADATA
fxtrade-0.1.7.dist-info/WHEEL
fxtrade-0.1.7.dist-info/RECORD
