Metadata-Version: 2.3
Name: fxtrade
Version: 0.1.7
Summary: 
License: MIT
Author: wsuzume
Author-email: joshnobus@gmail.com
Requires-Python: >=3.9,<4.0
Classifier: License :: OSI Approved :: MIT License
Classifier: Programming Language :: Python :: 3
Classifier: Programming Language :: Python :: 3.9
Classifier: Programming Language :: Python :: 3.10
Classifier: Programming Language :: Python :: 3.11
Classifier: Programming Language :: Python :: 3.12
Classifier: Programming Language :: Python :: 3.13
Requires-Dist: pydantic (>=2.11.1,<3.0.0)
Requires-Dist: requests (>=2.32.3,<3.0.0)
